cybernum/__init__.py
cybernum-1.0.0.dist-info/LICENSE
cybernum-1.0.0.dist-info/METADATA
cybernum-1.0.0.dist-info/WHEEL
cybernum-1.0.0.dist-info/top_level.txt
cybernum-1.0.0.dist-info/RECORD
