Metadata-Version: 2.1
Name: cybernum
Version: 1.0.0
Summary: Cyber Number
Home-page: https://github.com/muzudho/cyber-number-notation
Author: muzudho
Author-email: muzudho1@gmail.com
Project-URL: Bug Tracker, https://github.com/muzudho/cyber-number-notation/issues
Classifier: Programming Language :: Python :: 3
Classifier: License :: OSI Approved :: MIT License
Classifier: Operating System :: OS Independent
Requires-Python: >=3.6
License-File: LICENSE
